LICENSE
MANIFEST.in
README.md
requirements.txt
setup.cfg
setup.py
notebook_wide_screen/__init__.py
notebook_wide_screen/__meta__.py
notebook_wide_screen/wide_screen.py
notebook_wide_screen.egg-info/PKG-INFO
notebook_wide_screen.egg-info/SOURCES.txt
notebook_wide_screen.egg-info/dependency_links.txt
notebook_wide_screen.egg-info/requires.txt
notebook_wide_screen.egg-info/top_level.txt
notebook_wide_screen/templates/main.html
notebook_wide_screen/templates/notice_long.md
notebook_wide_screen/templates/notice_safe.txt
notebook_wide_screen/templates/notice_short.md
notebook_wide_screen/templates/wideScreen.css