Metadata-Version: 1.1
Name: notebook-wide-screen
Version: 0.1.1
Summary: Enable user to display notebook in very wide screens - if notebook is trusted
Home-page: https://github.com/oscar6echo/notebook_wide_screen
Author: oscar6echo
Author-email: olivier.borderies@gmail.com
License: MIT
Download-URL: https://github.com/oscar6echo/notebook_wide_screen/tarball/0.1.1
Keywords: python,display,css
Platform: UNKNOWN
Classifier: Development Status :: 4 - Beta
Classifier: License :: OSI Approved :: MIT License
Classifier: Programming Language :: Python :: 2.7
Classifier: Programming Language :: Python :: 3.5
Classifier: Programming Language :: Python :: 3.6
